django_updown-1.1.0.dist-info/DESCRIPTION.rst
django_updown-1.1.0.dist-info/METADATA
django_updown-1.1.0.dist-info/RECORD
django_updown-1.1.0.dist-info/WHEEL
django_updown-1.1.0.dist-info/metadata.json
django_updown-1.1.0.dist-info/top_level.txt
tests/__init__.py
tests/conftest.py
tests/models.py
tests/test_model.py
updown/__init__.py
updown/exceptions.py
updown/fields.py
updown/forms.py
updown/models.py
updown/views.py
updown/migrations/0001_initial.py
updown/migrations/__init__.py
